{
  "name": "Luna",
  "level": 3,
  "alignment": "Neutral Good",
  "abilities": [
    {
      "name": "Strength",
      "baseScore": 15,
      "featIncrease": 0,
      "backgroundIncrease": 0,
      "miscIncrease": 0
    },
    {
      "name": "Dexterity",
      "baseScore": 8,
      "featIncrease": 0,
      "backgroundIncrease": 0,
      "miscIncrease": 0
    },
    {
      "name": "Constitution",
      "baseScore": 15,
      "featIncrease": 0,
      "backgroundIncrease": 0,
      "miscIncrease": 0
    },
    {
      "name": "Intelligence",
      "baseScore": 8,
      "featIncrease": 0,
      "backgroundIncrease": 0,
      "miscIncrease": 0
    },
    {
      "name": "Wisdom",
      "baseScore": 15,
      "featIncrease": 0,
      "backgroundIncrease": 0,
      "miscIncrease": 0
    },
    {
      "name": "Charisma",
      "baseScore": 8,
      "featIncrease": 0,
      "backgroundIncrease": 0,
      "miscIncrease": 0
    }
  ],
  "background": "",
  "class": {
    "name": "Cleric",
    "subclass": {
      "name": "Life",
      "type": ""
    },
    "divineOrder": "",
    "primalOrder": ""
  },
  "expertSkills": [],
  "feats": [],
  "fightingStyles": [],
  "race": {
    "name": "Elf",
    "subrace": {
      "name": "Wood Elf",
      "description": ""
    }
  },
  "immunities": [],
  "inventory": {
    "backpack": [
      "Rope",
      "Silk",
      "Ration*5",
      "Blanket",
      "Caltrops",
      "Case",
      "Clothes",
      "traveler's",
      "Crossbow bolt*20",
      "Crowbar",
      "Dice Set",
      "Disguise Kit",
      "Thieves' Tools",
      "Forgery Kit",
      "Climber's Kit",
      "Fishing tackle",
      "Grappling hook",
      "Tinderbox",
      "Waterskin"
    ],
    "equipped": [
      "Half Plate",
      "Shield",
      "Longsword",
      "Longbow"
    ],
    "gold": 10,
    "magicItems": []
  },
  "languages": [
    "Common",
    "Elvish",
    "Celestial",
    "Dwarvish"
  ],
  "resistances": [],
  "skillProficiencies": [
    "Medicine",
    "Nature"
  ],
  "specialActions": [],
  "spells": [
    "Guidance",
    "Sacred Flame",
    "Spare the Dying",
    "Bane",
    "Bless",
    "Cure Wounds",
    "Guiding Bolt",
    "Healing Word",
    "Aid",
    "Prayer of Healing"
  ],
  "rules": "5e",
  "xp": 0,
  "xpMode": "milestone",
  "imagePath": "images/Luna.png",
  "_fileName": "Cleric.json",
  "originalFileName": "Cleric.json"
}